sfnx/__init__.py
sfnx/db.py
sfnx/main.py
sfnx/security.py
sfnx-0.2.2.dist-info/LICENSE
sfnx-0.2.2.dist-info/METADATA
sfnx-0.2.2.dist-info/WHEEL
sfnx-0.2.2.dist-info/entry_points.txt
sfnx-0.2.2.dist-info/top_level.txt
sfnx-0.2.2.dist-info/RECORD
