Metadata-Version: 2.1
Name: sfnx
Version: 0.2.2
Classifier: Programming Language :: Python :: 3
Classifier: Programming Language :: Python :: 3.7
Classifier: Programming Language :: Python :: 3.8
Classifier: Programming Language :: Python :: 3.9
Classifier: License :: OSI Approved :: MIT License
Classifier: Operating System :: OS Independent
Requires-Python: >=3.7
License-File: LICENSE
Requires-Dist: typer[all] <1.0,>=0.9.0
Requires-Dist: rich <14.0,>=13.6.0
Requires-Dist: cryptography <42.0,>=41.0.4
Requires-Dist: argon2-cffi <24.0,>=23.1.0
Requires-Dist: sqlmodel <0.1.0,>=0.0.11
Requires-Dist: pyperclip <2.0,>=1.8.2
